{
    "AX": {
        "error": 0.00888638907035348,
        "error_type": "SEM",
        "filter_outliers_dict": {
            "filter_outliers": true,
            "iterations": 1,
            "std_devs": 2
        },
        "fit": "Average",
        "fn": 43,
        "include_baseline_error": false,
        "n": 45,
        "reviewed": true,
        "value": -0.038138465528094835
    },
    "CDD": {
        "error": 5.719915588543384e-06,
        "error_type": "SEM",
        "filter_outliers_dict": {
            "filter_outliers": true,
            "iterations": 1,
            "std_devs": 10
        },
        "fit": "Average",
        "fn": 45,
        "include_baseline_error": false,
        "n": 45,
        "reviewed": true,
        "value": 1.0140326533777019e-05
    },
    "H1": {
        "error": 0.006254947946414314,
        "error_type": "SEM",
        "filter_outliers_dict": {
            "filter_outliers": true,
            "iterations": 1,
            "std_devs": 2
        },
        "fit": "Average",
        "fn": 44,
        "include_baseline_error": false,
        "n": 45,
        "reviewed": true,
        "value": 0.014664107531147734
    },
    "H2": {
        "error": 0.007369184308188329,
        "error_type": "SEM",
        "filter_outliers_dict": {
            "filter_outliers": true,
            "iterations": 1,
            "std_devs": 2
        },
        "fit": "average",
        "value": 0.02371881612525096
    },
    "L1": {
        "error": 0.002076134667159438,
        "error_type": "SEM",
        "filter_outliers_dict": {
            "filter_outliers": true,
            "iterations": 1,
            "std_devs": 2
        },
        "fit": "Average",
        "fn": 43,
        "include_baseline_error": false,
        "n": 45,
        "reviewed": true,
        "value": 0.025181057957694108
    },
    "L2": {
        "error": 0.007479226944973482,
        "error_type": "SEM",
        "filter_outliers_dict": {
            "filter_outliers": true,
            "iterations": 1,
            "std_devs": 2
        },
        "fit": "Average",
        "fn": 45,
        "include_baseline_error": false,
        "n": 45,
        "reviewed": true,
        "value": 0.05719039655135324
    }
}